pytest_logfest/__init__.py
pytest_logfest/hooks.py
pytest_logfest/logging_classes.py
pytest_logfest/plugin.py
pytest_logfest-0.3.0.dist-info/DESCRIPTION.rst
pytest_logfest-0.3.0.dist-info/METADATA
pytest_logfest-0.3.0.dist-info/RECORD
pytest_logfest-0.3.0.dist-info/WHEEL
pytest_logfest-0.3.0.dist-info/entry_points.txt
pytest_logfest-0.3.0.dist-info/metadata.json
pytest_logfest-0.3.0.dist-info/top_level.txt
